sql_lineage/__init__.py
sql_lineage/__main__.py
sql_lineage/lineage.py
sql_lineage/main.py
bills_sql_lineage-0.0.5.dist-info/METADATA
bills_sql_lineage-0.0.5.dist-info/WHEEL
bills_sql_lineage-0.0.5.dist-info/entry_points.txt
bills_sql_lineage-0.0.5.dist-info/top_level.txt
bills_sql_lineage-0.0.5.dist-info/RECORD
