Metadata-Version: 2.4
Name: bills-sql-lineage
Version: 0.0.5
Summary: Personal SQL lineage generator.
Author: billwallis
Requires-Python: >=3.11
Requires-Dist: arguably>=1.2.5
Requires-Dist: sqlglot[rs]>=26.12.1
